setup.cfg
setup.py
leryan/__init__.py
leryan.types.egg-info/PKG-INFO
leryan.types.egg-info/SOURCES.txt
leryan.types.egg-info/dependency_links.txt
leryan.types.egg-info/requires.txt
leryan.types.egg-info/top_level.txt
leryan/types/__init__.py
leryan/types/fastenum.py
leryan/types/objectdict.py
leryan/types/simpleconf.py
test/__init__.py
test/test_fastenum.py
test/test_objectdict.py
test/test_simpleconf.py