Metadata-Version: 1.1
Name: leryan.types
Version: 0.0.17
Summary: some "types": classes derived from python dict, list...
Home-page: https://github.com/Leryan/leryan.types
Author: Florent Peterschmitt
Author-email: florent@peterschmitt.fr
License: MIT
Platform: UNKNOWN
Classifier: Programming Language :: Python :: 2.7
Classifier: Programming Language :: Python :: 3.4
Classifier: Programming Language :: Python :: 3.5
Classifier: Programming Language :: Python :: 3.6
